bilibili/__init__.py
bilibili_utils-0.1.dist-info/LICENSE
bilibili_utils-0.1.dist-info/METADATA
bilibili_utils-0.1.dist-info/WHEEL
bilibili_utils-0.1.dist-info/top_level.txt
bilibili_utils-0.1.dist-info/RECORD
