Metadata-Version: 2.1
Name: bilibili-utils
Version: 0.1
Summary: Bilibili Utilities
Home-page: https://github.com/Iydon/bilibili-utils
Author: Iydon Liang
Author-email: liangiydon@gmail.com
License: MIT License
Platform: UNKNOWN
Classifier: Programming Language :: Python :: 3
Classifier: License :: OSI Approved :: MIT License
Classifier: Operating System :: OS Independent
Requires-Python: >=3.6
Requires-Dist: selenium
Requires-Dist: tqdm
Requires-Dist: requests
Requires-Dist: faker
Requires-Dist: matplotlib
Requires-Dist: aiohttp
Requires-Dist: sqlalchemy
Requires-Dist: lxml
Requires-Dist: bs4
Requires-Dist: rsa
Requires-Dist: pymusic-dl
Requires-Dist: fuzzywuzzy
Requires-Dist: retrying
Requires-Dist: pyexecjs
Requires-Dist: langid
